requests_html.py
docs/index.md
docs/requests-htmlc/requests_html.md
ext/requests-html-logo.ai
tests/python.html
tests/test_internet.py
tests/test_requests_html.py
requests_htmlc-0.0.8.dist-info/LICENSE
requests_htmlc-0.0.8.dist-info/METADATA
requests_htmlc-0.0.8.dist-info/WHEEL
requests_htmlc-0.0.8.dist-info/top_level.txt
requests_htmlc-0.0.8.dist-info/RECORD
