Metadata-Version: 2.1
Name: requests-htmlc
Version: 0.0.8
Summary: Fork of requests-html, powered by playwright
Author: Christian Boin
License: MIT License
Requires-Python: >=3.11
License-File: LICENSE
Requires-Dist: beautifulsoup4==4.12.3
Requires-Dist: certifi==2024.12.14
Requires-Dist: charset-normalizer==3.4.0
Requires-Dist: cssselect==1.2.0
Requires-Dist: fake-useragent==2.0.3
Requires-Dist: greenlet==3.1.1
Requires-Dist: idna==3.10
Requires-Dist: lxml==5.3.0
Requires-Dist: lxml_html_clean==0.4.1
Requires-Dist: parse==1.20.2
Requires-Dist: playwright==1.49.1
Requires-Dist: pyee==12.0.0
Requires-Dist: pyquery==2.0.1
Requires-Dist: requests==2.32.3
Requires-Dist: soupsieve==2.6
Requires-Dist: typing_extensions==4.12.2
Requires-Dist: urllib3==2.2.3
Requires-Dist: w3lib==2.2.1
Provides-Extra: dev
Requires-Dist: black; extra == "dev"
Requires-Dist: click; extra == "dev"
Requires-Dist: isort; extra == "dev"
Requires-Dist: pytest; extra == "dev"
Requires-Dist: pytest-cov; extra == "dev"
Requires-Dist: requests-file; extra == "dev"
Requires-Dist: pytest-asyncio; extra == "dev"
Requires-Dist: mkdocs; extra == "dev"
Requires-Dist: mkdocs-material; extra == "dev"
Requires-Dist: mike; extra == "dev"
Requires-Dist: mkdocstrings-python; extra == "dev"
Provides-Extra: package
Requires-Dist: build; extra == "package"
Requires-Dist: twine; extra == "package"
